diego/__init__.py
diego/basic.py
diego/basic_train.py
diego/core.py
diego/regressor.py
diego/study.py
diego/trials.py
diego/bayes_opt/__init__.py
diego/bayes_opt/classifier.py
diego/classifier/__init__.py
diego/classifier/base.py
diego/classifier/gradient_boosting.py
diego/classifier/logistic_regression.py
diego/classifier/logistic_regression_sk.py
diego/core/__init__.py
diego/core/storage.py
diego/depens/__init__.py
diego/depens/core.py
diego/depens/logging.py
diego/ensemble_net/__init__.py
diego/ensemble_net/base.py
diego/ensemble_net/combination.py
diego/ensemble_net/stacker.py
diego/generation/__init__.py
diego/generation/classifier.py
diego/metrics/__init__.py
diego/metrics/metrics.py
diego/preprocessor/__init__.py
diego/preprocessor/auto_binning.py
diego/preprocessor/base_binning.py
diego/preprocessor/lda.py
diego/preprocessor/local_uncertainty_sampling.py
diego_benchmark/__init__.py
diego_benchmark/base_benchmark.py
diego_benchmark/diego_titanic.py
diego-0.2.7.dist-info/LICENSE
diego-0.2.7.dist-info/METADATA
diego-0.2.7.dist-info/WHEEL
diego-0.2.7.dist-info/top_level.txt
diego-0.2.7.dist-info/RECORD
