Metadata-Version: 2.1
Name: diego
Version: 0.2.7
Summary: Diego: Data IntElliGence Out.
Home-page: https://github.com/lai-bluejay/diego
Author: Charles Lai
Author-email: lai.bluejay@gmail.com
License: MIT
Platform: UNKNOWN
Classifier: License :: OSI Approved :: MIT License
Classifier: Programming Language :: Python
Classifier: Programming Language :: Python :: 3
Classifier: Programming Language :: Python :: 3.6
Classifier: Programming Language :: Python :: Implementation :: CPython
Classifier: Programming Language :: Python :: Implementation :: PyPy
Requires-Python: >=3.6.0
Requires-Dist: numpy (>=1.16.2)
Requires-Dist: scipy (>=0.19.0)
Requires-Dist: scikit-learn (>=0.23)
Requires-Dist: deap (>=1.0)
Requires-Dist: update-checker (>=0.16)
Requires-Dist: tqdm (>=4.26.0)
Requires-Dist: stopit (>=1.1.1)
Requires-Dist: pandas (>=1.0)
Requires-Dist: xgboost
Requires-Dist: pyrfr (<0.9,>=0.7)
Requires-Dist: distributed
Requires-Dist: dask
Requires-Dist: smac (>=0.8)
Requires-Dist: ConfigSpace (<0.5,>=0.4.14)
Requires-Dist: auto-sklearn (>=0.11)
Requires-Dist: liac-arff
Requires-Dist: sklearn-contrib-lightning
